pylyrics2/__init__.py
pylyrics2/clean_text.py
pylyrics2/download_data.py
pylyrics2/extract_lyrics.py
pylyrics2/plot_cloud.py
pylyrics2-1.0.9.dist-info/LICENSE
pylyrics2-1.0.9.dist-info/WHEEL
pylyrics2-1.0.9.dist-info/METADATA
pylyrics2-1.0.9.dist-info/RECORD
