Metadata-Version: 2.1
Name: pylyrics2
Version: 1.0.9
Summary: This package helps you extract and analyse lyrics like a piece of cake!
License: MIT
Author: Group 2
Requires-Python: >=3.9,<4.0
Classifier: License :: OSI Approved :: MIT License
Classifier: Programming Language :: Python :: 3
Classifier: Programming Language :: Python :: 3.10
Classifier: Programming Language :: Python :: 3.9
Requires-Dist: beautifulsoup4 (>=4.10.0,<5.0.0)
Requires-Dist: kaggle (>=1.5.12,<2.0.0)
Requires-Dist: matplotlib (>=3.5.1,<4.0.0)
Requires-Dist: pandas (>=1.3.5,<2.0.0)
Requires-Dist: requests (>=2.27.1,<3.0.0)
Requires-Dist: wordcloud (>=1.8.1,<2.0.0)
